piperabm/__init__.py
piperabm/exceptions.py
piperabm/resource.py
piperabm/economy/__init__.py
piperabm/economy/accessibility.py
piperabm/economy/trade/__init__.py
piperabm/economy/trade/allocation.py
piperabm/economy/trade/nash_bargaining.py
piperabm/economy/trade/trade_solver.py
piperabm/economy/trade/samples/trade_0.py
piperabm/economy/trade/samples/trade_1.py
piperabm/economy/trade/samples/trade_2.py
piperabm/economy/trade/samples/trade_3.py
piperabm/economy/trade/samples/trade_4.py
piperabm/infrastructure/__init__.py
piperabm/infrastructure/degradation.py
piperabm/infrastructure/generate.py
piperabm/infrastructure/heuristic_paths.py
piperabm/infrastructure/infrastructure.py
piperabm/infrastructure/path.py
piperabm/infrastructure/serialize.py
piperabm/infrastructure/stat.py
piperabm/infrastructure/update.py
piperabm/infrastructure/grammar/__init__.py
piperabm/infrastructure/grammar/grammar.py
piperabm/infrastructure/grammar/rules/__init__.py
piperabm/infrastructure/grammar/rules/rule_0.py
piperabm/infrastructure/grammar/rules/rule_1.py
piperabm/infrastructure/grammar/rules/rule_2.py
piperabm/infrastructure/grammar/rules/rule_3.py
piperabm/infrastructure/graphics/__init__.py
piperabm/infrastructure/graphics/graphics.py
piperabm/infrastructure/graphics/style.py
piperabm/infrastructure/query/__init__.py
piperabm/infrastructure/query/add.py
piperabm/infrastructure/query/get.py
piperabm/infrastructure/query/query.py
piperabm/infrastructure/query/set.py
piperabm/infrastructure/samples/__init__.py
piperabm/infrastructure/samples/infrastructure_0.py
piperabm/infrastructure/samples/infrastructure_1.py
piperabm/infrastructure/samples/infrastructure_2.py
piperabm/infrastructure/samples/infrastructure_3.py
piperabm/model/__init__.py
piperabm/model/file.py
piperabm/model/model.py
piperabm/model/serialize.py
piperabm/model/trade.py
piperabm/model/update.py
piperabm/model/graphics/__init__.py
piperabm/model/graphics/graphics.py
piperabm/model/graphics/style.py
piperabm-0.2.0.dist-info/licenses/LICENSE
piperabm-0.2.0.dist-info/METADATA
piperabm-0.2.0.dist-info/WHEEL
piperabm-0.2.0.dist-info/top_level.txt
piperabm-0.2.0.dist-info/RECORD
