Metadata-Version: 2.4
Name: piperabm
Version: 0.2.0
Summary: An Agent-Based Model Framework for Simulating Resilience in Python
Author-email: Aslan Noorghasemi <aslann@cmu.edu>, Sierra Hicks <sh2337@cornell.edu>, Christopher McComb <ccm@cmu.edu>
License: MIT
Classifier: Programming Language :: Python :: 3
Classifier: License :: OSI Approved :: MIT License
Classifier: Operating System :: OS Independent
Classifier: Topic :: Scientific/Engineering
Requires-Python: >=3.10
License-File: LICENSE
Requires-Dist: keepdelta
Requires-Dist: matplotlib==3.10.1
Requires-Dist: networkx==3.4.2
Requires-Dist: numpy==2.2.5
Requires-Dist: scipy==1.15.2
Dynamic: license-file
